AUTHORS
CHANGELOG.txt
DESCRIPTION
LICENSE
MANIFEST.in
README.rst
setup.cfg
setup.py
account_keeping/__init__.py
account_keeping/admin.py
account_keeping/forms.py
account_keeping/freckle_api.py
account_keeping/models.py
account_keeping/urls.py
account_keeping/utils.py
account_keeping/views.py
account_keeping/fixtures/account_keeping.json
account_keeping/management/__init__.py
account_keeping/management/commands/__init__.py
account_keeping/management/commands/collect_invoices.py
account_keeping/management/commands/importer_mmex.py
account_keeping/migrations/0001_initial.py
account_keeping/migrations/0002_auto_20161006_1403.py
account_keeping/migrations/0003_auto_20171223_0356.py
account_keeping/migrations/0004_branch.py
account_keeping/migrations/0005_auto_20190102_0349.py
account_keeping/migrations/0006_auto_20190102_1114.py
account_keeping/migrations/0007_auto_20190121_1334.py
account_keeping/migrations/0008_auto_20190121_1336.py
account_keeping/migrations/__init__.py
account_keeping/south_migrations/0001_initial.py
account_keeping/south_migrations/0002_auto__add_field_invoice_description.py
account_keeping/south_migrations/0003_auto__add_field_invoice_value_net__add_field_invoice_value_gross.py
account_keeping/south_migrations/0004_init_invoice_value_fields.py
account_keeping/south_migrations/0005_move_rates_to_history_app.py
account_keeping/south_migrations/0006_auto__del_currencyrate__del_currency.py
account_keeping/south_migrations/__init__.py
account_keeping/static/account_keeping/css/bootstrap.min.css
account_keeping/static/account_keeping/css/styles.css
account_keeping/static/account_keeping/fonts/glyphicons-halflings-regular.eot
account_keeping/static/account_keeping/fonts/glyphicons-halflings-regular.svg
account_keeping/static/account_keeping/fonts/glyphicons-halflings-regular.ttf
account_keeping/static/account_keeping/fonts/glyphicons-halflings-regular.woff
account_keeping/static/account_keeping/js/account_keeping.js
django_account_keeping.egg-info/PKG-INFO
django_account_keeping.egg-info/SOURCES.txt
django_account_keeping.egg-info/dependency_links.txt
django_account_keeping.egg-info/requires.txt
django_account_keeping.egg-info/top_level.txt