Metadata-Version: 1.0
Name: django-account-keeping
Version: 0.4.4
Summary: A reusable Django app for keeping track of transactions in your bank accounts.
